{
  "crop": "小白菜-奶油白",
  "market": "台北二",
  "train_rows": 76,
  "test_rows": 30,
  "best_model": "MLP-50x50",
  "metrics": {
    "MAE": 25.178572552177535,
    "RMSE": 29.35349051362161,
    "MAPE%": 55.270169594496934
  },
  "last_obs_date": "2025-08-13",
  "last_price": 85.8,
  "forecast_date": "2025-08-14",
  "forecast_price": 142.78476774792347,
  "forecast_series": [
    {
      "date": "2025-08-14",
      "price": 142.78476774792347
    },
    {
      "date": "2025-08-15",
      "price": 191.56265578614324
    },
    {
      "date": "2025-08-16",
      "price": 253.6776619785031
    },
    {
      "date": "2025-08-17",
      "price": 328.64343744474246
    },
    {
      "date": "2025-08-18",
      "price": 425.97363393230563
    },
    {
      "date": "2025-08-19",
      "price": 548.2207519926023
    },
    {
      "date": "2025-08-20",
      "price": 700.9736818595521
    },
    {
      "date": "2025-08-21",
      "price": 912.5832842814043
    },
    {
      "date": "2025-08-22",
      "price": 1192.7879257421341
    },
    {
      "date": "2025-08-23",
      "price": 1564.6834081493075
    },
    {
      "date": "2025-08-24",
      "price": 2046.9032204471882
    },
    {
      "date": "2025-08-25",
      "price": 2677.5715702440602
    },
    {
      "date": "2025-08-26",
      "price": 3500.9939793781555
    },
    {
      "date": "2025-08-27",
      "price": 4575.0175819298365
    }
  ],
  "baselines": {
    "naive": 85.8,
    "ma7": 88.79999999999998
  },
  "history": [
    {
      "date": "2025-03-18",
      "price": 31.6,
      "volume": 594
    },
    {
      "date": "2025-03-19",
      "price": 35.3,
      "volume": 518
    },
    {
      "date": "2025-03-20",
      "price": 28.4,
      "volume": 410
    },
    {
      "date": "2025-03-21",
      "price": 37.5,
      "volume": 420
    },
    {
      "date": "2025-03-22",
      "price": 34.6,
      "volume": 648
    },
    {
      "date": "2025-03-23",
      "price": 55.1,
      "volume": 420
    },
    {
      "date": "2025-03-25",
      "price": 47.2,
      "volume": 624
    },
    {
      "date": "2025-03-26",
      "price": 42.6,
      "volume": 700
    },
    {
      "date": "2025-03-27",
      "price": 31.0,
      "volume": 753
    },
    {
      "date": "2025-03-28",
      "price": 21.8,
      "volume": 951
    },
    {
      "date": "2025-03-29",
      "price": 17.5,
      "volume": 2159
    },
    {
      "date": "2025-03-30",
      "price": 32.9,
      "volume": 908
    },
    {
      "date": "2025-04-01",
      "price": 25.7,
      "volume": 1293
    },
    {
      "date": "2025-04-02",
      "price": 28.8,
      "volume": 1220
    },
    {
      "date": "2025-04-03",
      "price": 28.0,
      "volume": 1834
    },
    {
      "date": "2025-04-06",
      "price": 30.4,
      "volume": 1051
    },
    {
      "date": "2025-04-08",
      "price": 24.1,
      "volume": 2153
    },
    {
      "date": "2025-04-09",
      "price": 22.5,
      "volume": 2183
    },
    {
      "date": "2025-04-11",
      "price": 20.0,
      "volume": 1639
    },
    {
      "date": "2025-04-12",
      "price": 21.8,
      "volume": 1110
    },
    {
      "date": "2025-04-13",
      "price": 19.4,
      "volume": 995
    },
    {
      "date": "2025-04-15",
      "price": 21.9,
      "volume": 1312
    },
    {
      "date": "2025-04-16",
      "price": 14.7,
      "volume": 1435
    },
    {
      "date": "2025-04-17",
      "price": 10.0,
      "volume": 1679
    },
    {
      "date": "2025-04-18",
      "price": 15.299999999999999,
      "volume": 1366
    },
    {
      "date": "2025-04-19",
      "price": 16.5,
      "volume": 1576
    },
    {
      "date": "2025-04-20",
      "price": 13.400000000000002,
      "volume": 1724
    },
    {
      "date": "2025-04-22",
      "price": 12.6,
      "volume": 1743
    },
    {
      "date": "2025-04-23",
      "price": 9.7,
      "volume": 2142
    },
    {
      "date": "2025-04-24",
      "price": 7.2,
      "volume": 1407
    },
    {
      "date": "2025-04-25",
      "price": 9.2,
      "volume": 1264
    },
    {
      "date": "2025-04-26",
      "price": 11.3,
      "volume": 1173
    },
    {
      "date": "2025-04-27",
      "price": 9.2,
      "volume": 2096
    },
    {
      "date": "2025-04-29",
      "price": 13.1,
      "volume": 1556
    },
    {
      "date": "2025-04-30",
      "price": 14.7,
      "volume": 1006
    },
    {
      "date": "2025-05-01",
      "price": 13.1,
      "volume": 1141
    },
    {
      "date": "2025-05-02",
      "price": 13.200000000000001,
      "volume": 1266
    },
    {
      "date": "2025-05-03",
      "price": 10.7,
      "volume": 2142
    },
    {
      "date": "2025-05-04",
      "price": 9.5,
      "volume": 2098
    },
    {
      "date": "2025-05-06",
      "price": 14.5,
      "volume": 1899
    },
    {
      "date": "2025-05-07",
      "price": 9.3,
      "volume": 2980
    },
    {
      "date": "2025-05-09",
      "price": 10.2,
      "volume": 1931
    },
    {
      "date": "2025-05-10",
      "price": 7.699999999999999,
      "volume": 2214
    },
    {
      "date": "2025-05-11",
      "price": 5.3,
      "volume": 1683
    },
    {
      "date": "2025-05-13",
      "price": 9.4,
      "volume": 1975
    },
    {
      "date": "2025-05-14",
      "price": 9.8,
      "volume": 2230
    },
    {
      "date": "2025-05-15",
      "price": 8.8,
      "volume": 1246
    },
    {
      "date": "2025-05-16",
      "price": 8.3,
      "volume": 1682
    },
    {
      "date": "2025-05-17",
      "price": 8.4,
      "volume": 1390
    },
    {
      "date": "2025-05-18",
      "price": 8.5,
      "volume": 1627
    },
    {
      "date": "2025-05-20",
      "price": 15.8,
      "volume": 1318
    },
    {
      "date": "2025-05-21",
      "price": 13.699999999999998,
      "volume": 1302
    },
    {
      "date": "2025-05-22",
      "price": 8.7,
      "volume": 656
    },
    {
      "date": "2025-05-23",
      "price": 16.4,
      "volume": 690
    },
    {
      "date": "2025-05-24",
      "price": 13.5,
      "volume": 1348
    },
    {
      "date": "2025-05-25",
      "price": 8.1,
      "volume": 1707
    },
    {
      "date": "2025-05-27",
      "price": 13.6,
      "volume": 1036
    },
    {
      "date": "2025-05-28",
      "price": 11.1,
      "volume": 1541
    },
    {
      "date": "2025-05-29",
      "price": 10.1,
      "volume": 957
    },
    {
      "date": "2025-05-30",
      "price": 17.5,
      "volume": 838
    },
    {
      "date": "2025-05-31",
      "price": 22.0,
      "volume": 1003
    },
    {
      "date": "2025-06-03",
      "price": 9.9,
      "volume": 1324
    },
    {
      "date": "2025-06-04",
      "price": 14.5,
      "volume": 794
    },
    {
      "date": "2025-06-05",
      "price": 15.5,
      "volume": 1056
    },
    {
      "date": "2025-06-06",
      "price": 18.7,
      "volume": 648
    },
    {
      "date": "2025-06-07",
      "price": 18.9,
      "volume": 716
    },
    {
      "date": "2025-06-08",
      "price": 17.2,
      "volume": 1372
    },
    {
      "date": "2025-06-10",
      "price": 29.6,
      "volume": 906
    },
    {
      "date": "2025-06-11",
      "price": 24.7,
      "volume": 997
    },
    {
      "date": "2025-06-12",
      "price": 28.4,
      "volume": 470
    },
    {
      "date": "2025-06-13",
      "price": 32.2,
      "volume": 222
    },
    {
      "date": "2025-06-14",
      "price": 32.8,
      "volume": 622
    },
    {
      "date": "2025-06-15",
      "price": 25.1,
      "volume": 966
    },
    {
      "date": "2025-06-17",
      "price": 31.4,
      "volume": 517
    },
    {
      "date": "2025-06-18",
      "price": 30.2,
      "volume": 494
    },
    {
      "date": "2025-06-20",
      "price": 27.9,
      "volume": 420
    },
    {
      "date": "2025-06-21",
      "price": 16.3,
      "volume": 1072
    },
    {
      "date": "2025-06-22",
      "price": 32.9,
      "volume": 526
    },
    {
      "date": "2025-06-24",
      "price": 36.1,
      "volume": 389
    },
    {
      "date": "2025-06-25",
      "price": 27.7,
      "volume": 417
    },
    {
      "date": "2025-06-26",
      "price": 27.0,
      "volume": 235
    },
    {
      "date": "2025-06-27",
      "price": 23.8,
      "volume": 663
    },
    {
      "date": "2025-06-28",
      "price": 25.4,
      "volume": 631
    },
    {
      "date": "2025-06-29",
      "price": 20.8,
      "volume": 858
    },
    {
      "date": "2025-07-01",
      "price": 24.7,
      "volume": 554
    },
    {
      "date": "2025-07-02",
      "price": 17.9,
      "volume": 523
    },
    {
      "date": "2025-07-03",
      "price": 13.0,
      "volume": 460
    },
    {
      "date": "2025-07-04",
      "price": 27.2,
      "volume": 380
    },
    {
      "date": "2025-07-05",
      "price": 43.9,
      "volume": 493
    },
    {
      "date": "2025-07-06",
      "price": 39.1,
      "volume": 855
    },
    {
      "date": "2025-07-08",
      "price": 44.2,
      "volume": 252
    },
    {
      "date": "2025-07-09",
      "price": 26.2,
      "volume": 348
    },
    {
      "date": "2025-07-10",
      "price": 65.0,
      "volume": 60
    },
    {
      "date": "2025-07-11",
      "price": 22.8,
      "volume": 571
    },
    {
      "date": "2025-07-12",
      "price": 27.5,
      "volume": 376
    },
    {
      "date": "2025-07-13",
      "price": 42.8,
      "volume": 332
    },
    {
      "date": "2025-07-15",
      "price": 63.79999999999999,
      "volume": 134
    },
    {
      "date": "2025-07-16",
      "price": 54.9,
      "volume": 325
    },
    {
      "date": "2025-07-18",
      "price": 47.8,
      "volume": 362
    },
    {
      "date": "2025-07-19",
      "price": 62.0,
      "volume": 415
    },
    {
      "date": "2025-07-20",
      "price": 62.9,
      "volume": 413
    },
    {
      "date": "2025-07-22",
      "price": 53.5,
      "volume": 772
    },
    {
      "date": "2025-07-23",
      "price": 32.0,
      "volume": 587
    },
    {
      "date": "2025-07-24",
      "price": 34.2,
      "volume": 216
    },
    {
      "date": "2025-07-25",
      "price": 40.70000000000001,
      "volume": 227
    },
    {
      "date": "2025-07-26",
      "price": 47.79999999999999,
      "volume": 404
    },
    {
      "date": "2025-07-27",
      "price": 78.8,
      "volume": 192
    },
    {
      "date": "2025-07-29",
      "price": 80.7,
      "volume": 362
    },
    {
      "date": "2025-07-30",
      "price": 69.9,
      "volume": 183
    },
    {
      "date": "2025-07-31",
      "price": 39.4,
      "volume": 389
    },
    {
      "date": "2025-08-01",
      "price": 30.9,
      "volume": 420
    },
    {
      "date": "2025-08-02",
      "price": 39.8,
      "volume": 1038
    },
    {
      "date": "2025-08-03",
      "price": 43.1,
      "volume": 672
    },
    {
      "date": "2025-08-05",
      "price": 50.1,
      "volume": 388
    },
    {
      "date": "2025-08-06",
      "price": 55.3,
      "volume": 517
    },
    {
      "date": "2025-08-07",
      "price": 63.0,
      "volume": 282
    },
    {
      "date": "2025-08-08",
      "price": 114.0,
      "volume": 174
    },
    {
      "date": "2025-08-09",
      "price": 93.0,
      "volume": 275
    },
    {
      "date": "2025-08-10",
      "price": 104.0,
      "volume": 262
    },
    {
      "date": "2025-08-12",
      "price": 106.5,
      "volume": 380
    },
    {
      "date": "2025-08-13",
      "price": 85.8,
      "volume": 637
    }
  ]
}